allennlp/__init__.py
allennlp/pretrained.py
allennlp/run.py
allennlp/version.py
allennlp/commands/__init__.py
allennlp/commands/configure.py
allennlp/commands/dry_run.py
allennlp/commands/elmo.py
allennlp/commands/evaluate.py
allennlp/commands/find_learning_rate.py
allennlp/commands/fine_tune.py
allennlp/commands/make_vocab.py
allennlp/commands/predict.py
allennlp/commands/print_results.py
allennlp/commands/subcommand.py
allennlp/commands/test_install.py
allennlp/commands/train.py
allennlp/common/__init__.py
allennlp/common/checks.py
allennlp/common/configuration.py
allennlp/common/file_utils.py
allennlp/common/from_params.py
allennlp/common/params.py
allennlp/common/registrable.py
allennlp/common/tee_logger.py
allennlp/common/tqdm.py
allennlp/common/util.py
allennlp/common/testing/__init__.py
allennlp/common/testing/model_test_case.py
allennlp/common/testing/test_case.py
allennlp/data/__init__.py
allennlp/data/dataset.py
allennlp/data/instance.py
allennlp/data/vocabulary.py
allennlp/data/dataset_readers/__init__.py
allennlp/data/dataset_readers/babi.py
allennlp/data/dataset_readers/ccgbank.py
allennlp/data/dataset_readers/conll2000.py
allennlp/data/dataset_readers/conll2003.py
allennlp/data/dataset_readers/copynet_seq2seq.py
allennlp/data/dataset_readers/dataset_reader.py
allennlp/data/dataset_readers/event2mind.py
allennlp/data/dataset_readers/interleaving_dataset_reader.py
allennlp/data/dataset_readers/language_modeling.py
allennlp/data/dataset_readers/masked_language_modeling.py
allennlp/data/dataset_readers/multiprocess_dataset_reader.py
allennlp/data/dataset_readers/next_token_lm.py
allennlp/data/dataset_readers/ontonotes_ner.py
allennlp/data/dataset_readers/penn_tree_bank.py
allennlp/data/dataset_readers/quora_paraphrase.py
allennlp/data/dataset_readers/semantic_dependency_parsing.py
allennlp/data/dataset_readers/semantic_role_labeling.py
allennlp/data/dataset_readers/seq2seq.py
allennlp/data/dataset_readers/sequence_tagging.py
allennlp_pvt_nightly-0.9.1.dev201910011800.dist-info/LICENSE
allennlp_pvt_nightly-0.9.1.dev201910011800.dist-info/METADATA
allennlp_pvt_nightly-0.9.1.dev201910011800.dist-info/WHEEL
allennlp_pvt_nightly-0.9.1.dev201910011800.dist-info/entry_points.txt
allennlp_pvt_nightly-0.9.1.dev201910011800.dist-info/top_level.txt
allennlp_pvt_nightly-0.9.1.dev201910011800.dist-info/RECORD
