Metadata-Version: 2.1
Name: allennlp-pvt-nightly
Version: 0.9.1.dev201910011800
Summary: An open-source NLP research library, built on PyTorch.
Home-page: https://github.com/allenai/allennlp
Author: Allen Institute for Artificial Intelligence
Author-email: allennlp@allenai.org
License: Apache
Keywords: allennlp NLP deep learning machine reading
Platform: UNKNOWN
Classifier: Intended Audience :: Science/Research
Classifier: Development Status :: 3 - Alpha
Classifier: License :: OSI Approved :: Apache Software License
Classifier: Programming Language :: Python :: 3.6
Classifier: Topic :: Scientific/Engineering :: Artificial Intelligence
Requires-Python: >=3.6.1
Requires-Dist: torch (>=1.2.0)
Requires-Dist: overrides
Requires-Dist: nltk
Requires-Dist: spacy (<2.2,>=2.1.0)
Requires-Dist: numpy
Requires-Dist: tensorboardX (>=1.2)
Requires-Dist: boto3
Requires-Dist: flask (>=1.0.2)
Requires-Dist: flask-cors (>=3.0.7)
Requires-Dist: gevent (>=1.3.6)
Requires-Dist: requests (>=2.18)
Requires-Dist: tqdm (>=4.19)
Requires-Dist: editdistance
Requires-Dist: h5py
Requires-Dist: scikit-learn
Requires-Dist: scipy
Requires-Dist: pytz (>=2017.3)
Requires-Dist: unidecode
Requires-Dist: matplotlib (>=2.2.3)
Requires-Dist: pytest
Requires-Dist: flaky
Requires-Dist: responses (>=0.7)
Requires-Dist: numpydoc (>=0.8.0)
Requires-Dist: conllu (==1.3.1)
Requires-Dist: parsimonious (>=0.8.0)
Requires-Dist: ftfy
Requires-Dist: sqlparse (>=0.2.4)
Requires-Dist: word2number (>=1.1)
Requires-Dist: pytorch-pretrained-bert (>=0.6.0)
Requires-Dist: pytorch-transformers (>=1.1.0)
Requires-Dist: jsonpickle
Requires-Dist: jsonnet (>=0.10.0) ; sys_platform != "win32"
